nanocore/app.py
nanocore/broker.py
nanocore/cli.py
nanocore/config.py
nanocore/rpn_worker.py
nanocore/schema.py
nanocore/sha1_worker.py
nanocore/subprocess_worker.py
nanocore/worker.py
nanocore/ws_manager.py
nanocore/workers/code_ops.py
nanocore/workers/dependency.py
nanocore/workers/generator.py
nanocore/workers/task_automation.py
nanocore-0.1.1.dist-info/METADATA
nanocore-0.1.1.dist-info/WHEEL
nanocore-0.1.1.dist-info/entry_points.txt
nanocore-0.1.1.dist-info/licenses/AUTHORS.rst
nanocore-0.1.1.dist-info/licenses/LICENSE
nanocore-0.1.1.dist-info/RECORD
