Metadata-Version: 2.4
Name: nanocore
Version: 0.1.1
Summary: Add your description here
License-File: AUTHORS.rst
License-File: LICENSE
Requires-Python: >=3.12
Requires-Dist: fastapi>=0.128.0
Requires-Dist: python-dotenv>=1.2.1
Requires-Dist: typer>=0.21.1
Requires-Dist: uvicorn>=0.40.0
Requires-Dist: websockets>=16.0
